MANIFEST.in
README.md
build.py
pyproject.toml
requirements-dev.txt
requirements.txt
setup.py
test.py
genetic_algo/attributes.py
genetic_algo/driver.py
genetic_algo/environment.py
genetic_algo/solution.py
genetic_algo.egg-info/PKG-INFO
genetic_algo.egg-info/SOURCES.txt
genetic_algo.egg-info/dependency_links.txt
genetic_algo.egg-info/requires.txt
genetic_algo.egg-info/top_level.txt