Metadata-Version: 2.1
Name: genetic-algo
Version: 0.1.0
Summary: A framework for developing Genetic-Algorithm programs to solve problems dynamically and explicitly.
Home-page: https://github.com/Shahaf-F-S/auto-screener
Author: Shahaf Frank-Shapir
Author-email: shahaffrs@gmail.com
License: MIT
Classifier: Intended Audience :: Developers
Classifier: License :: OSI Approved :: MIT License
Classifier: Programming Language :: Python
Classifier: Programming Language :: Python :: 3
Classifier: Programming Language :: Python :: 3.8
Classifier: Programming Language :: Python :: 3.9
Classifier: Programming Language :: Python :: 3.10
Classifier: Programming Language :: Python :: 3.11
Classifier: Operating System :: OS Independent
Provides-Extra: dev
